odoo8_addon_pos_margin-8.0.1.0.0-py2.7-nspkg.pth
odoo8_addon_pos_margin-8.0.1.0.0.dist-info/DESCRIPTION.rst
odoo8_addon_pos_margin-8.0.1.0.0.dist-info/METADATA
odoo8_addon_pos_margin-8.0.1.0.0.dist-info/RECORD
odoo8_addon_pos_margin-8.0.1.0.0.dist-info/WHEEL
odoo8_addon_pos_margin-8.0.1.0.0.dist-info/metadata.json
odoo8_addon_pos_margin-8.0.1.0.0.dist-info/namespace_packages.txt
odoo8_addon_pos_margin-8.0.1.0.0.dist-info/top_level.txt
odoo_addons/pos_margin/README.rst
odoo_addons/pos_margin/__init__.py
odoo_addons/pos_margin/__openerp__.py
odoo_addons/pos_margin/i18n/fr.po
odoo_addons/pos_margin/models/__init__.py
odoo_addons/pos_margin/models/pos_order.py
odoo_addons/pos_margin/models/pos_order_line.py
odoo_addons/pos_margin/static/description/pos_order_form.png
odoo_addons/pos_margin/views/view_pos_order.xml
