Metadata-Version: 2.0
Name: odoo8-addon-pos-margin
Version: 8.0.1.0.0
Summary: Margin on PoS Order
Home-page: UNKNOWN
Author: GRAP,Odoo Community Association (OCA)
Author-email: support@odoo-community.org
License: UNKNOWN
Platform: UNKNOWN
Classifier: Programming Language :: Python :: 2.7
Classifier: Framework :: Odoo
Requires-Dist: odoo (<9.0a,>=8.0a)
